{ "tema": 22, "titulo": "Tecnología y comunicación", "conceptos": [
{"id":"a1-t22-001","es":"internet","en":{"texto":"internet","ejemplo":"I need internet.","pron":"IN-ter-net"},"fr":{"texto":"internet","ejemplo":"J'ai besoin d'internet.","pron":"en-ter-NET"}},
{"id":"a1-t22-002","es":"correo electrónico","en":{"texto":"email","ejemplo":"I sent an email.","pron":"I-meil"},"fr":{"texto":"e-mail","ejemplo":"J'ai envoyé un e-mail.","pron":"i-MEL"}},
{"id":"a1-t22-003","es":"mensaje","en":{"texto":"message","ejemplo":"I got your message.","pron":"ME-sich"},"fr":{"texto":"message","ejemplo":"J'ai reçu ton message.","pron":"me-SAZH"}},
{"id":"a1-t22-004","es":"aplicación","en":{"texto":"app","ejemplo":"This app is useful.","pron":"AP"},"fr":{"texto":"appli","ejemplo":"Cette appli est utile.","pron":"a-PLI"}},
{"id":"a1-t22-005","es":"sitio web","en":{"texto":"website","ejemplo":"The website is slow.","pron":"UEB-sait"},"fr":{"texto":"site web","ejemplo":"Le site web est lent.","pron":"sit UEB"}},
{"id":"a1-t22-006","es":"pantalla","en":{"texto":"screen","ejemplo":"The screen is big.","pron":"SKRIN"},"fr":{"texto":"écran","ejemplo":"L'écran est grand.","pron":"e-KRAN"}},
{"id":"a1-t22-007","es":"contraseña","en":{"texto":"password","ejemplo":"I forgot my password.","pron":"PAS-uerd"},"fr":{"texto":"mot de passe","ejemplo":"J'ai oublié mon mot de passe.","pron":"mo de PAS"}},
{"id":"a1-t22-008","es":"descargar","en":{"texto":"to download","ejemplo":"I downloaded the app.","pron":"tu DAUN-loud"},"fr":{"texto":"télécharger","ejemplo":"J'ai téléchargé l'appli.","pron":"te-le-shar-ZHE"}},
{"id":"a1-t22-009","es":"enviar","en":{"texto":"to send","ejemplo":"I send a message.","pron":"tu SEND"},"fr":{"texto":"envoyer","ejemplo":"J'envoie un message.","pron":"an-vua-YE"}},
{"id":"a1-t22-010","es":"llamar","en":{"texto":"to call","ejemplo":"I call my mother.","pron":"tu KOL"},"fr":{"texto":"appeler","ejemplo":"J'appelle ma mère.","pron":"ap-LE"}},
{"id":"a1-t22-011","es":"escribir un texto","en":{"texto":"to text","ejemplo":"I text my friend.","pron":"tu TEKST"},"fr":{"texto":"envoyer un texto","ejemplo":"J'envoie un texto à mon ami.","pron":"an-vua-YE un teks-TO"}},
{"id":"a1-t22-012","es":"hacer clic","en":{"texto":"to click","ejemplo":"Click here, please.","pron":"tu KLIK"},"fr":{"texto":"cliquer","ejemplo":"Cliquez ici, s'il vous plaît.","pron":"kli-KE"}},
{"id":"a1-t22-013","es":"abrir","en":{"texto":"to open","ejemplo":"Open the app.","pron":"tu OU-pen"},"fr":{"texto":"ouvrir","ejemplo":"Ouvre l'appli.","pron":"u-VRIR"}},
{"id":"a1-t22-014","es":"en línea","en":{"texto":"online","ejemplo":"I am online now.","pron":"on-LAIN"},"fr":{"texto":"en ligne","ejemplo":"Je suis en ligne maintenant.","pron":"an LIÑ"}},
{"id":"a1-t22-015","es":"red","en":{"texto":"network","ejemplo":"The network is slow.","pron":"NET-uerk"},"fr":{"texto":"réseau","ejemplo":"Le réseau est lent.","pron":"re-SO"}},
{"id":"a1-t22-016","es":"archivo","en":{"texto":"file","ejemplo":"I opened the file.","pron":"FAIL"},"fr":{"texto":"fichier","ejemplo":"J'ai ouvert le fichier.","pron":"fi-SHYE"}},
{"id":"a1-t22-017","es":"foto","en":{"texto":"photo","ejemplo":"I took a photo.","pron":"FOU-tou"},"fr":{"texto":"photo","ejemplo":"J'ai pris une photo.","pron":"fo-TO"}},
{"id":"a1-t22-018","es":"video","en":{"texto":"video","ejemplo":"I watched a video.","pron":"VI-di-ou"},"fr":{"texto":"vidéo","ejemplo":"J'ai regardé une vidéo.","pron":"vi-de-O"}},
{"id":"a1-t22-019","es":"ayer","en":{"texto":"yesterday","ejemplo":"I called you yesterday.","pron":"YES-ter-dei"},"fr":{"texto":"hier","ejemplo":"Je t'ai appelé hier.","pron":"YER"}},
{"id":"a1-t22-020","es":"pasado (último)","en":{"texto":"last","ejemplo":"Last week I studied a lot.","pron":"LAST"},"fr":{"texto":"dernier","ejemplo":"La semaine dernière, j'ai beaucoup étudié.","pron":"der-NYE"}},
{"id":"a1-t22-021","es":"guardar","en":{"texto":"to save","ejemplo":"I save the file.","pron":"tu SEIV"},"fr":{"texto":"enregistrer","ejemplo":"J'enregistre le fichier.","pron":"an-re-zhis-TRE"}},
{"id":"a1-t22-022","es":"buscar","en":{"texto":"to search","ejemplo":"I search on the internet.","pron":"tu SERCH"},"fr":{"texto":"chercher","ejemplo":"Je cherche sur internet.","pron":"sher-SHE"}},
{"id":"a1-t22-023","es":"teclado","en":{"texto":"keyboard","ejemplo":"The keyboard is black.","pron":"KI-bord"},"fr":{"texto":"clavier","ejemplo":"Le clavier est noir.","pron":"kla-VYE"}},
{"id":"a1-t22-024","es":"ratón (mouse)","en":{"texto":"mouse","ejemplo":"The mouse is here.","pron":"MAUS"},"fr":{"texto":"souris","ejemplo":"La souris est ici.","pron":"su-RI"}},
{"id":"a1-t22-025","es":"wifi","en":{"texto":"wifi","ejemplo":"Is there wifi here?","pron":"UAI-fai"},"fr":{"texto":"wifi","ejemplo":"Il y a du wifi ici ?","pron":"ui-FI"}},
{"id":"a1-t22-026","es":"cámara","en":{"texto":"camera","ejemplo":"The camera is good.","pron":"KA-me-ra"},"fr":{"texto":"caméra","ejemplo":"La caméra est bonne.","pron":"ka-me-RA"}},
{"id":"a1-t22-027","es":"batería","en":{"texto":"battery","ejemplo":"The battery is low.","pron":"BA-te-ri"},"fr":{"texto":"batterie","ejemplo":"La batterie est faible.","pron":"ba-TRI"}},
{"id":"a1-t22-028","es":"cargar","en":{"texto":"to charge","ejemplo":"I charge my phone.","pron":"tu CHARCH"},"fr":{"texto":"charger","ejemplo":"Je charge mon téléphone.","pron":"shar-ZHE"}},
{"id":"a1-t22-029","es":"apagar","en":{"texto":"to turn off","ejemplo":"Turn off the computer.","pron":"tu tern OF"},"fr":{"texto":"éteindre","ejemplo":"Éteins l'ordinateur.","pron":"e-TENDR"}},
{"id":"a1-t22-030","es":"encender","en":{"texto":"to turn on","ejemplo":"Turn on the light.","pron":"tu tern ON"},"fr":{"texto":"allumer","ejemplo":"Allume la lumière.","pron":"a-lü-ME"}},
{"id":"a1-t22-031","es":"redes sociales","en":{"texto":"social media","ejemplo":"I use social media every day.","pron":"SOU-shal MI-dia"},"fr":{"texto":"réseaux sociaux","ejemplo":"J'utilise les réseaux sociaux tous les jours.","pron":"re-so so-SYO"}}
] }
