{ "tema": 21, "titulo": "Universidad y estudios", "conceptos": [
{"id":"a1-t21-001","es":"universidad","en":{"texto":"university","ejemplo":"I study at the university.","pron":"yu-ni-VER-si-ti"},"fr":{"texto":"université","ejemplo":"J'étudie à l'université.","pron":"ü-ni-ver-si-TE"}},
{"id":"a1-t21-002","es":"clase","en":{"texto":"class","ejemplo":"The class starts at nine.","pron":"KLAS"},"fr":{"texto":"cours","ejemplo":"Le cours commence à neuf heures.","pron":"KUR"}},
{"id":"a1-t21-003","es":"materia","en":{"texto":"subject","ejemplo":"My subject is difficult.","pron":"SAB-yekt"},"fr":{"texto":"matière","ejemplo":"Ma matière est difficile.","pron":"ma-TYER"}},
{"id":"a1-t21-004","es":"examen","en":{"texto":"exam","ejemplo":"I have an exam today.","pron":"ig-SAM"},"fr":{"texto":"examen","ejemplo":"J'ai un examen aujourd'hui.","pron":"eg-za-MEN"}},
{"id":"a1-t21-005","es":"tarea","en":{"texto":"homework","ejemplo":"I do a lot of homework.","pron":"JOUM-uerk"},"fr":{"texto":"devoirs","ejemplo":"Je fais beaucoup de devoirs.","pron":"de-VUAR"}},
{"id":"a1-t21-006","es":"nota (calificación)","en":{"texto":"grade","ejemplo":"I have a good grade.","pron":"GREID"},"fr":{"texto":"note","ejemplo":"J'ai une bonne note.","pron":"NOT"}},
{"id":"a1-t21-007","es":"salón","en":{"texto":"classroom","ejemplo":"The classroom is big.","pron":"KLAS-rum"},"fr":{"texto":"salle de classe","ejemplo":"La salle de classe est grande.","pron":"sal de KLAS"}},
{"id":"a1-t21-008","es":"informática","en":{"texto":"computer science","ejemplo":"I study computer science.","pron":"kom-PIU-ter SAI-ens"},"fr":{"texto":"informatique","ejemplo":"J'étudie l'informatique.","pron":"en-for-ma-TIK"},"nota":"Tu carrera."},
{"id":"a1-t21-009","es":"matemáticas","en":{"texto":"maths","ejemplo":"Maths is difficult.","pron":"MATHS"},"fr":{"texto":"maths","ejemplo":"Les maths sont difficiles.","pron":"MAT"}},
{"id":"a1-t21-010","es":"aprender","en":{"texto":"to learn","ejemplo":"I learn French.","pron":"tu LERN"},"fr":{"texto":"apprendre","ejemplo":"J'apprends le français.","pron":"a-PRANDR"}},
{"id":"a1-t21-011","es":"enseñar","en":{"texto":"to teach","ejemplo":"She teaches maths.","pron":"tu TICH"},"fr":{"texto":"enseigner","ejemplo":"Elle enseigne les maths.","pron":"an-se-ÑE"}},
{"id":"a1-t21-012","es":"aprobar","en":{"texto":"to pass","ejemplo":"I want to pass the exam.","pron":"tu PAS"},"fr":{"texto":"réussir","ejemplo":"Je veux réussir l'examen.","pron":"re-ü-SIR"}},
{"id":"a1-t21-013","es":"reprobar","en":{"texto":"to fail","ejemplo":"I don't want to fail.","pron":"tu FEIL"},"fr":{"texto":"échouer","ejemplo":"Je ne veux pas échouer.","pron":"e-shu-E"}},
{"id":"a1-t21-014","es":"difícil","en":{"texto":"difficult","ejemplo":"The exam is difficult.","pron":"DI-fi-kolt"},"fr":{"texto":"difficile","ejemplo":"L'examen est difficile.","pron":"di-fi-SIL"}},
{"id":"a1-t21-015","es":"fácil","en":{"texto":"easy","ejemplo":"This subject is easy.","pron":"I-si"},"fr":{"texto":"facile","ejemplo":"Cette matière est facile.","pron":"fa-SIL"}},
{"id":"a1-t21-016","es":"porque","en":{"texto":"because","ejemplo":"I study because I like it.","pron":"bi-KOS"},"fr":{"texto":"parce que","ejemplo":"J'étudie parce que j'aime ça.","pron":"pars-KE"}},
{"id":"a1-t21-017","es":"entonces","en":{"texto":"so","ejemplo":"It's easy, so I like it.","pron":"SOU"},"fr":{"texto":"donc","ejemplo":"C'est facile, donc j'aime ça.","pron":"DONK"}},
{"id":"a1-t21-018","es":"entender","en":{"texto":"to understand","ejemplo":"I understand the lesson.","pron":"tu an-der-STAND"},"fr":{"texto":"comprendre","ejemplo":"Je comprends la leçon.","pron":"kon-PRANDR"}},
{"id":"a1-t21-019","es":"biblioteca","en":{"texto":"library","ejemplo":"I study at the library.","pron":"LAI-bre-ri"},"fr":{"texto":"bibliothèque","ejemplo":"J'étudie à la bibliothèque.","pron":"bi-blyo-TEK"}},
{"id":"a1-t21-020","es":"carrera (título)","en":{"texto":"degree","ejemplo":"My degree is in computer science.","pron":"di-GRI"},"fr":{"texto":"diplôme","ejemplo":"Mon diplôme est en informatique.","pron":"di-PLOM"}},
{"id":"a1-t21-021","es":"pregunta","en":{"texto":"question","ejemplo":"I have a question.","pron":"KUES-chon"},"fr":{"texto":"question","ejemplo":"J'ai une question.","pron":"kes-TYON"}},
{"id":"a1-t21-022","es":"respuesta","en":{"texto":"answer","ejemplo":"The answer is easy.","pron":"AN-ser"},"fr":{"texto":"réponse","ejemplo":"La réponse est facile.","pron":"re-PONS"}},
{"id":"a1-t21-023","es":"ciencia","en":{"texto":"science","ejemplo":"I like science.","pron":"SAI-ens"},"fr":{"texto":"science","ejemplo":"J'aime la science.","pron":"SYANS"}},
{"id":"a1-t21-024","es":"historia","en":{"texto":"history","ejemplo":"History is interesting.","pron":"JIS-to-ri"},"fr":{"texto":"histoire","ejemplo":"L'histoire est intéressante.","pron":"is-TUAR"}},
{"id":"a1-t21-025","es":"compañero","en":{"texto":"classmate","ejemplo":"He is my classmate.","pron":"KLAS-meit"},"fr":{"texto":"camarade","ejemplo":"C'est mon camarade.","pron":"ka-ma-RAD"}},
{"id":"a1-t21-026","es":"estudiar","en":{"texto":"to study","ejemplo":"I study every night.","pron":"tu STA-di"},"fr":{"texto":"étudier","ejemplo":"J'étudie tous les soirs.","pron":"e-tü-DYE"}},
{"id":"a1-t21-027","es":"apuntes","en":{"texto":"notes","ejemplo":"I take notes in class.","pron":"NOUTS"},"fr":{"texto":"notes","ejemplo":"Je prends des notes en cours.","pron":"NOT"}},
{"id":"a1-t21-028","es":"diccionario","en":{"texto":"dictionary","ejemplo":"I use a dictionary.","pron":"DIK-sho-ne-ri"},"fr":{"texto":"dictionnaire","ejemplo":"J'utilise un dictionnaire.","pron":"dik-syo-NER"}},
{"id":"a1-t21-029","es":"beca","en":{"texto":"scholarship","ejemplo":"I have a scholarship.","pron":"SKO-lar-ship"},"fr":{"texto":"bourse","ejemplo":"J'ai une bourse.","pron":"BURS"}},
{"id":"a1-t21-030","es":"practicar","en":{"texto":"to practise","ejemplo":"I practise every day.","pron":"tu PRAK-tis"},"fr":{"texto":"pratiquer","ejemplo":"Je pratique tous les jours.","pron":"pra-ti-KE"}}
] }
