{ "tema": 4, "idioma": "fr", "titulo": "Posesivos y la posesión con de",
"regla": "Los posesivos concuerdan con lo poseído: mon/ma/mes (mi), ton/ta/tes (tu), son/sa/ses (su), notre/votre/leur. La posesión con nombres usa 'de': 'le frère de Marie' (el hermano de Marie). Ante palabra femenina que empieza por vocal se usa mon/ton/son: 'mon amie'.",
"trampa": "'son/sa' no indican el género del dueño sino de lo poseído: 'sa sœur' = su hermana (de él o de ella).",
"ejemplos": [
{"frase":"Mon frère est étudiant.","traduccion":"Mi hermano es estudiante."},
{"frase":"C'est le frère de Marie.","traduccion":"Es el hermano de Marie."},
{"frase":"Mon amie est gentille.","traduccion":"Mi amiga es amable."}
],
"ejercicios": [
{"tipo":"hueco","enunciado":"___ frère est étudiant. (mi)","respuesta":"mon"},
{"tipo":"hueco","enunciado":"___ sœur est jeune. (mi)","respuesta":"ma"},
{"tipo":"hueco","enunciado":"C'est le frère ___ Marie.","respuesta":"de"},
{"tipo":"hueco","enunciado":"___ amie est gentille. (mi, ante vocal)","respuesta":"mon"},
{"tipo":"opcion_multiple","enunciado":"___ parents habitent au Pérou. (mis)","opciones":["Mes","Mon","Ma"],"respuesta":"Mes"},
{"tipo":"opcion_multiple","enunciado":"el hermano de Paul = le frère ___ Paul.","opciones":["de","à","le"],"respuesta":"de"},
{"tipo":"opcion_multiple","enunciado":"Marie et ___ sœur. (su, de ella)","opciones":["sa","son","ses"],"respuesta":"sa"},
{"tipo":"ordenar","enunciado":"Ordena: mi hermano es alto.","opciones":["mon","frère","est","grand"],"respuesta":"mon frère est grand"},
{"tipo":"ordenar","enunciado":"Ordena: es la hermana de Paul.","opciones":["c'est","la","sœur","de","Paul"],"respuesta":"c'est la sœur de Paul"},
{"tipo":"ordenar","enunciado":"Ordena: mi madre es amable.","opciones":["ma","mère","est","gentille"],"respuesta":"ma mère est gentille"},
{"tipo":"corregir_error","enunciado":"Ma ami est gentille.","respuesta":"Mon amie est gentille."},
{"tipo":"corregir_error","enunciado":"C'est le frère à Marie.","respuesta":"C'est le frère de Marie."},
{"tipo":"corregir_error","enunciado":"Mon sœur est jeune.","respuesta":"Ma sœur est jeune."},
{"tipo":"traducir","enunciado":"Mi hermano es estudiante.","respuesta":"Mon frère est étudiant.","aceptadas":["mon frère est etudiant"]},
{"tipo":"traducir","enunciado":"Es el hermano de Marie.","respuesta":"C'est le frère de Marie.","aceptadas":["c'est le frère de marie"]}
] }
